Metadata-Version: 2.1
Name: asma-bmi
Version: 0.1
Summary: simple library in python for test 
Author: Asma-Salah
